PhantomDE/__init__.py
PhantomDE-0.1.2.dist-info/LICENCE.txt
PhantomDE-0.1.2.dist-info/METADATA
PhantomDE-0.1.2.dist-info/WHEEL
PhantomDE-0.1.2.dist-info/top_level.txt
PhantomDE-0.1.2.dist-info/RECORD
