Metadata-Version: 2.1
Name: PhantomDE
Version: 0.1.2
Summary: Simple way to decode and encode strings!
Home-page: http://packages.python.org/PhantomDE
Author: Robert Jones
Author-email: robertcwad@gmail.com
Keywords: Python
License-File: LICENCE.txt
